{
  "type": "minecraft:crafting_shaped",
  "category": "equipment",
  "key": {
    "#": [
      {
        "item": "minecraft:cod"
      },
      {
        "item": "minecraft:salmon"
      },
      {
        "item": "minecraft:pufferfish"
      },
      {
        "item": "minecraft:tropical_fish"
      }
    ],
    "&": {
      "item": "moblassos:golden_lasso"
    },
    "X": {
      "item": "minecraft:lapis_lazuli"
    }
  },
  "pattern": [
    " X ",
    "#&#",
    " X "
  ],
  "result": {
    "item": "moblassos:aqua_lasso"
  }
}